{
	"format_version": "1.8.0",
	"animations": {
		"prepare": {
			"loop": "hold_on_last_frame",
			"animation_length": 1.5,
			"bones": {
				"bone": {
					"rotation": {
						"0.0": {
							"vector": [0, 720, 0]
						},
						"0.75": {
							"vector": [0, 0, 0]
						}
					},
					"position": {
						"0.0": {
							"vector": [0, 0, 0]
						},
						"0.375": {
							"vector": [0, 4, 0]
						},
						"0.75": {
							"vector": [0, 0, 0]
						},
						"1.125": {
							"vector": [0, 4, 0]
						},
						"1.4167": {
							"vector": [0, 0, 0]
						}
					},
					"scale": {
						"0.0": {
							"vector": [0.3, 0.3, 0.3]
						},
						"0.75": {
							"vector": [1.5, 1.5, 1.5]
						},
						"1.5": {
							"vector": [1.5, 1.5, 1.5]
						}
					}
				}
			}
		}
	},
	"geckolib_format_version": 2
}